dailyrevenue/__init__.py
dailyrevenue/dailyrevenue.py
daily_publisher_revenue-1.0.dist-info/METADATA
daily_publisher_revenue-1.0.dist-info/WHEEL
daily_publisher_revenue-1.0.dist-info/top_level.txt
daily_publisher_revenue-1.0.dist-info/RECORD
